rephacheck/__init__.py
rephacheck/rephacheck.json
rephacheck/server.py
rephacheck-0.4.2.dist-info/DESCRIPTION.rst
rephacheck-0.4.2.dist-info/METADATA
rephacheck-0.4.2.dist-info/RECORD
rephacheck-0.4.2.dist-info/WHEEL
rephacheck-0.4.2.dist-info/entry_points.txt
rephacheck-0.4.2.dist-info/metadata.json
rephacheck-0.4.2.dist-info/top_level.txt
