Metadata-Version: 2.0
Name: rephacheck
Version: 0.4.2
Summary: Health check for PostgreSQL cluster managed by repmgr
Home-page: https://github.com/UbiCastTeam/rephacheck
Author: Nicolas KAROLAK @ UbiCast
Author-email: nicolas@karolak.fr
License: LGPLv3
Download-URL: https://github.com/UbiCastTeam/rephacheck/archive/v0.4.2.tar.gz
Keywords: haproxy healthcheck postgresql repmgr
Platform: UNKNOWN
Classifier: Development Status :: 4 - Beta
Classifier: Intended Audience :: System Administrators
Classifier: License :: OSI Approved :: GNU Lesser General Public License v3 (LGPLv3)
Classifier: Natural Language :: English
Classifier: Operating System :: POSIX :: Linux
Classifier: Operating System :: Unix
Classifier: Programming Language :: Python
Classifier: Programming Language :: Python :: 2
Classifier: Programming Language :: Python :: 2.7
Classifier: Programming Language :: Python :: 3
Classifier: Programming Language :: Python :: 3.6
Classifier: Topic :: Database
Classifier: Topic :: Internet :: Proxy Servers
Classifier: Topic :: Internet :: WWW/HTTP :: HTTP Servers
Requires-Python: >=2.7
Requires-Dist: future
Requires-Dist: psycopg2
